nextorch/__init__.py
nextorch/bo.py
nextorch/doe.py
nextorch/io.py
nextorch/parameter.py
nextorch/plotting.py
nextorch/utils.py
nextorch/test/__init__.py
nextorch/test/fructose_pfr_model_function.py
nextorch/test/test_1d_function.py
nextorch/test/test_EHVI.py
nextorch/test/test_input.xlsx
nextorch/test/test_io.py
nextorch/test/test_parameter.py
nextorch/test/test_plotting.py
nextorch-0.1.0.dist-info/LICENSE.md
nextorch-0.1.0.dist-info/METADATA
nextorch-0.1.0.dist-info/WHEEL
nextorch-0.1.0.dist-info/top_level.txt
nextorch-0.1.0.dist-info/RECORD
