Metadata-Version: 2.1
Name: nextorch
Version: 0.1.0
Summary: Experimental design and Bayesian optimization library in Python/PyTorch
Home-page: https://github.com/VlachosGroup/nextorch
Author: Vlachos Research Group
Author-email: vlachos@udel.edu
License: UNKNOWN
Project-URL: Documentation, https://nextorch.readthedocs.io/en/latest/
Project-URL: Source, https://github.com/VlachosGroup/nextorch
Platform: UNKNOWN
Classifier: Programming Language :: Python :: 3
Classifier: License :: OSI Approved :: MIT License
Classifier: Operating System :: OS Independent
Classifier: Intended Audience :: Science/Research
Classifier: Topic :: Scientific/Engineering :: Chemistry
Requires-Python: >=3.7
License-File: LICENSE.md
Requires-Dist: torch (>=1.8)
Requires-Dist: gpytorch (>=1.4)
Requires-Dist: botorch (>=0.4.0)
Requires-Dist: matplotlib (>=3.1.1)
Requires-Dist: pyDOE2 (>=1.3.0)
Requires-Dist: numpy (>=1.19.2)
Requires-Dist: scipy (>=1.3.1)
Requires-Dist: pandas (>=0.25.1)
Requires-Dist: openpyxl (>=3.0.7)
Requires-Dist: pytest (>=6.2.3)
